examples/__init__.py
examples/example_zoo.py
examples/run_flat.py
examples/run_hierarchical.py
examples/run_mixed.py
examples/run_single.py
examples/structures/__init__.py
examples/structures/flat.py
examples/structures/hierarchical.py
examples/structures/single.py
paiargparse/__init__.py
paiargparse/dataclass_extractor.py
paiargparse/dataclass_json_overrides.py
paiargparse/dataclass_meta.py
paiargparse/dataclass_parser.py
paiargparse/main_parser.py
paiargparse/param_tree.py
paiargparse/version.py
paiargparse-1.1.2.data/data/requirements.txt
test/__init__.py
test/dataclasse_setup.py
test/test_cmd_line.py
test/test_data_class.py
test/test_dataclass_json.py
test/test_dataclass_list.py
test/test_dataclass_set.py
test/test_default_value.py
test/test_dict.py
test/test_generic_data_class.py
test/test_ignore.py
test/test_meta.py
test/test_multi_args.py
test/test_optional.py
test/test_ssnake.py
test/test_subparser.py
test/test_types.py
paiargparse-1.1.2.dist-info/LICENSE
paiargparse-1.1.2.dist-info/METADATA
paiargparse-1.1.2.dist-info/WHEEL
paiargparse-1.1.2.dist-info/top_level.txt
paiargparse-1.1.2.dist-info/RECORD
