Metadata-Version: 2.1
Name: paiargparse
Version: 1.1.2
Summary: UNKNOWN
Home-page: https://github.com/Planet-AI-GmbH/paiargparse
Author: Planet AI GmbH
Author-email: admin@planet-ai.de
License: MIT
Download-URL: https://github.com/Planet-AI-GmbH/paiargparse/archive/1.1.2.tar.gz
Keywords: argument parser,dataclass,hierarchical
Platform: UNKNOWN
Requires-Python: >=3.7
Requires-Dist: dataclasses-json (==0.5.5)
Requires-Dist: editdistance
